oidcrp/__init__.py
oidcrp/client_auth.py
oidcrp/configure.py
oidcrp/cookie.py
oidcrp/defaults.py
oidcrp/entity.py
oidcrp/exception.py
oidcrp/http.py
oidcrp/logging.py
oidcrp/rp_handler.py
oidcrp/service.py
oidcrp/service_context.py
oidcrp/service_factory.py
oidcrp/state_interface.py
oidcrp/util.py
oidcrp/oauth2/__init__.py
oidcrp/oauth2/access_token.py
oidcrp/oauth2/authorization.py
oidcrp/oauth2/provider_info_discovery.py
oidcrp/oauth2/refresh_access_token.py
oidcrp/oauth2/utils.py
oidcrp/oauth2/add_on/__init__.py
oidcrp/oauth2/add_on/dpop.py
oidcrp/oauth2/add_on/pkce.py
oidcrp/oauth2/add_on/pushed_authorization.py
oidcrp/oauth2/client_credentials/__init__.py
oidcrp/oauth2/client_credentials/cc_access_token.py
oidcrp/oauth2/client_credentials/cc_refresh_access_token.py
oidcrp/oidc/__init__.py
oidcrp/oidc/access_token.py
oidcrp/oidc/authorization.py
oidcrp/oidc/check_id.py
oidcrp/oidc/check_session.py
oidcrp/oidc/end_session.py
oidcrp/oidc/provider_info_discovery.py
oidcrp/oidc/read_registration.py
oidcrp/oidc/refresh_access_token.py
oidcrp/oidc/registration.py
oidcrp/oidc/userinfo.py
oidcrp/oidc/utils.py
oidcrp/oidc/webfinger.py
oidcrp/provider/__init__.py
oidcrp/provider/github.py
oidcrp/provider/linkedin.py
oidcrp-2.1.4.dist-info/LICENSE
oidcrp-2.1.4.dist-info/METADATA
oidcrp-2.1.4.dist-info/WHEEL
oidcrp-2.1.4.dist-info/top_level.txt
oidcrp-2.1.4.dist-info/RECORD
