Metadata-Version: 2.1
Name: oidcrp
Version: 2.1.4
Summary: Python implementation of OAuth2 Client and OpenID Connect RP
Home-page: https://github.com/IdentityPython/oicrp/
Author: Roland Hedberg
Author-email: roland@catalogix.se
License: Apache 2.0
Platform: UNKNOWN
Classifier: Development Status :: 5 - Production/Stable
Classifier: License :: OSI Approved :: Apache Software License
Classifier: Programming Language :: Python :: 3.7
Classifier: Programming Language :: Python :: 3.8
Classifier: Programming Language :: Python :: 3.9
Classifier: Programming Language :: Python :: 3.10
Classifier: Topic :: Software Development :: Libraries :: Python Modules
License-File: LICENSE
Requires-Dist: oidcmsg (==1.6.0)
Requires-Dist: pyyaml (>=5.1.2)
Requires-Dist: responses
